{
  "type": "minecraft:crafting_shaped",
  "category": "misc",
  "key": {
    "A": {
      "item": "minecraft:amethyst_shard"
    },
    "P": [
      {
        "item": "minecraft:dirt"
      },
      {
        "item": "minecraft:cobblestone"
      }
    ],
    "S": {
      "tag": "c:stones"
    },
    "T": {
      "item": "manaweave_and_runes:earth_rune_carving_template"
    }
  },
  "pattern": [
    "STS",
    "SAS",
    "SPS"
  ],
  "result": {
    "count": 2,
    "id": "manaweave_and_runes:earth_rune_carving_template"
  }
}